luxafaret.py
luxafaret-1.3.0.dist-info/METADATA
luxafaret-1.3.0.dist-info/WHEEL
luxafaret-1.3.0.dist-info/entry_points.txt
luxafaret-1.3.0.dist-info/RECORD
