Metadata-Version: 2.1
Name: luxafaret
Version: 1.3.0
Summary: 🐍🐑🖍🎨🌈 Luxafåret - colourize your Luxafor flag from Python
License: ISC
Author: Simon Lundström
Author-email: github-commits@soy.se
Requires-Python: >=3.6.2,<4.0.0
Classifier: License :: OSI Approved
Classifier: Programming Language :: Python :: 3
Classifier: Programming Language :: Python :: 3.7
Classifier: Programming Language :: Python :: 3.8
Classifier: Programming Language :: Python :: 3.9
Classifier: Programming Language :: Python :: 3.10
Classifier: Programming Language :: Python :: 3.11
Classifier: Programming Language :: Python :: 3.12
Requires-Dist: hidapi (>=0.14,<0.15)
Requires-Dist: webcolors (>=1.11,<2.0)
